{
  "version": 1.0,
  "grid_size": 10,
  "tabs": [
    {
      "name": "Teleoperated",
      "grid_layout": {
        "layouts": [],
        "containers": [
          {
            "title": "modeName",
            "x": 740.0,
            "y": 390.0,
            "width": 120.0,
            "height": 120.0,
            "type": "Text Display",
            "properties": {
              "topic": "Robot/container/swerveProcessor/driveState/modeName",
              "period": 0.06,
              "data_type": "string",
              "show_submit_button": false
            }
          },
          {
            "title": "Radians",
            "x": 270.0,
            "y": 10.0,
            "width": 100.0,
            "height": 90.0,
            "type": "Text Display",
            "properties": {
              "topic": "Robot/container/drive/flModule/absoluteAngle/Radians",
              "period": 0.06,
              "data_type": "double",
              "show_submit_button": false
            }
          },
          {
            "title": "Position (units)",
            "x": 10.0,
            "y": 10.0,
            "width": 100.0,
            "height": 90.0,
            "type": "Text Display",
            "properties": {
              "topic": "Robot/container/drive/flModule/driveEncoder/Position (units)",
              "period": 0.06,
              "data_type": "double",
              "show_submit_button": false
            }
          },
          {
            "title": "Velocity (units per second)",
            "x": 10.0,
            "y": 100.0,
            "width": 100.0,
            "height": 70.0,
            "type": "Text Display",
            "properties": {
              "topic": "Robot/container/drive/flModule/driveEncoder/Velocity (units per second)",
              "period": 0.06,
              "data_type": "double",
              "show_submit_button": false
            }
          },
          {
            "title": "Error (units)",
            "x": 10.0,
            "y": 170.0,
            "width": 80.0,
            "height": 70.0,
            "type": "Text Display",
            "properties": {
              "topic": "Robot/container/drive/flModule/drivePID/Error (units)",
              "period": 0.06,
              "data_type": "double",
              "show_submit_button": false
            }
          },
          {
            "title": "Error over time (units per second)",
            "x": 10.0,
            "y": 240.0,
            "width": 140.0,
            "height": 70.0,
            "type": "Text Display",
            "properties": {
              "topic": "Robot/container/drive/flModule/drivePID/Error over time (units per second)",
              "period": 0.06,
              "data_type": "double",
              "show_submit_button": false
            }
          },
          {
            "title": "Accumulated error (units)",
            "x": 10.0,
            "y": 310.0,
            "width": 160.0,
            "height": 70.0,
            "type": "Text Display",
            "properties": {
              "topic": "Robot/container/drive/flModule/drivePID/Accumulated error (units)",
              "period": 0.06,
              "data_type": "double",
              "show_submit_button": false
            }
          },
          {
            "title": "Position (units)",
            "x": 170.0,
            "y": 10.0,
            "width": 100.0,
            "height": 90.0,
            "type": "Text Display",
            "properties": {
              "topic": "Robot/container/drive/flModule/turnEncoder/Position (units)",
              "period": 0.06,
              "data_type": "double",
              "show_submit_button": false
            }
          },
          {
            "title": "Velocity (units per second)",
            "x": 170.0,
            "y": 100.0,
            "width": 100.0,
            "height": 70.0,
            "type": "Text Display",
            "properties": {
              "topic": "Robot/container/drive/flModule/turnEncoder/Velocity (units per second)",
              "period": 0.06,
              "data_type": "double",
              "show_submit_button": false
            }
          },
          {
            "title": "Error (units)",
            "x": 170.0,
            "y": 170.0,
            "width": 110.0,
            "height": 70.0,
            "type": "Text Display",
            "properties": {
              "topic": "Robot/container/drive/flModule/turnPID/Error (units)",
              "period": 0.06,
              "data_type": "double",
              "show_submit_button": false
            }
          },
          {
            "title": "Error over time (units per second)",
            "x": 170.0,
            "y": 240.0,
            "width": 140.0,
            "height": 70.0,
            "type": "Text Display",
            "properties": {
              "topic": "Robot/container/drive/flModule/turnPID/Error over time (units per second)",
              "period": 0.06,
              "data_type": "double",
              "show_submit_button": false
            }
          },
          {
            "title": "Accumulated error (units)",
            "x": 170.0,
            "y": 310.0,
            "width": 160.0,
            "height": 70.0,
            "type": "Text Display",
            "properties": {
              "topic": "Robot/container/drive/flModule/turnPID/Accumulated error (units)",
              "period": 0.06,
              "data_type": "double",
              "show_submit_button": false
            }
          },
          {
            "title": "Setpoint position (units)",
            "x": 170.0,
            "y": 380.0,
            "width": 160.0,
            "height": 70.0,
            "type": "Text Display",
            "properties": {
              "topic": "Robot/container/drive/flModule/turnPID/Setpoint position (units)",
              "period": 0.06,
              "data_type": "double",
              "show_submit_button": false
            }
          },
          {
            "title": "Setpoint velocity (units per second)",
            "x": 170.0,
            "y": 450.0,
            "width": 150.0,
            "height": 70.0,
            "type": "Text Display",
            "properties": {
              "topic": "Robot/container/drive/flModule/turnPID/Setpoint velocity (units per second)",
              "period": 0.06,
              "data_type": "double",
              "show_submit_button": false
            }
          },
          {
            "title": "name",
            "x": 20.0,
            "y": 390.0,
            "width": 120.0,
            "height": 130.0,
            "type": "Text Display",
            "properties": {
              "topic": "Robot/container/drive/flModule/name",
              "period": 0.06,
              "data_type": "string",
              "show_submit_button": false
            }
          },
          {
            "title": "Radians",
            "x": 660.0,
            "y": 10.0,
            "width": 90.0,
            "height": 90.0,
            "type": "Text Display",
            "properties": {
              "topic": "Robot/container/drive/frModule/absoluteAngle/Radians",
              "period": 0.06,
              "data_type": "double",
              "show_submit_button": false
            }
          },
          {
            "title": "Position (units)",
            "x": 400.0,
            "y": 10.0,
            "width": 100.0,
            "height": 90.0,
            "type": "Text Display",
            "properties": {
              "topic": "Robot/container/drive/frModule/driveEncoder/Position (units)",
              "period": 0.06,
              "data_type": "double",
              "show_submit_button": false
            }
          },
          {
            "title": "Velocity (units per second)",
            "x": 400.0,
            "y": 100.0,
            "width": 100.0,
            "height": 70.0,
            "type": "Text Display",
            "properties": {
              "topic": "Robot/container/drive/frModule/driveEncoder/Velocity (units per second)",
              "period": 0.06,
              "data_type": "double",
              "show_submit_button": false
            }
          },
          {
            "title": "Error (units)",
            "x": 400.0,
            "y": 170.0,
            "width": 80.0,
            "height": 70.0,
            "type": "Text Display",
            "properties": {
              "topic": "Robot/container/drive/frModule/drivePID/Error (units)",
              "period": 0.06,
              "data_type": "double",
              "show_submit_button": false
            }
          },
          {
            "title": "Error over time (units per second)",
            "x": 400.0,
            "y": 240.0,
            "width": 140.0,
            "height": 70.0,
            "type": "Text Display",
            "properties": {
              "topic": "Robot/container/drive/frModule/drivePID/Error over time (units per second)",
              "period": 0.06,
              "data_type": "double",
              "show_submit_button": false
            }
          },
          {
            "title": "Accumulated error (units)",
            "x": 400.0,
            "y": 310.0,
            "width": 160.0,
            "height": 70.0,
            "type": "Text Display",
            "properties": {
              "topic": "Robot/container/drive/frModule/drivePID/Accumulated error (units)",
              "period": 0.06,
              "data_type": "double",
              "show_submit_button": false
            }
          },
          {
            "title": "Position (units)",
            "x": 560.0,
            "y": 10.0,
            "width": 100.0,
            "height": 90.0,
            "type": "Text Display",
            "properties": {
              "topic": "Robot/container/drive/frModule/turnEncoder/Position (units)",
              "period": 0.06,
              "data_type": "double",
              "show_submit_button": false
            }
          },
          {
            "title": "Velocity (units per second)",
            "x": 560.0,
            "y": 100.0,
            "width": 100.0,
            "height": 70.0,
            "type": "Text Display",
            "properties": {
              "topic": "Robot/container/drive/frModule/turnEncoder/Velocity (units per second)",
              "period": 0.06,
              "data_type": "double",
              "show_submit_button": false
            }
          },
          {
            "title": "Error (units)",
            "x": 560.0,
            "y": 170.0,
            "width": 80.0,
            "height": 70.0,
            "type": "Text Display",
            "properties": {
              "topic": "Robot/container/drive/frModule/turnPID/Error (units)",
              "period": 0.06,
              "data_type": "double",
              "show_submit_button": false
            }
          },
          {
            "title": "Error over time (units per second)",
            "x": 560.0,
            "y": 240.0,
            "width": 140.0,
            "height": 70.0,
            "type": "Text Display",
            "properties": {
              "topic": "Robot/container/drive/frModule/turnPID/Error over time (units per second)",
              "period": 0.06,
              "data_type": "double",
              "show_submit_button": false
            }
          },
          {
            "title": "Accumulated error (units)",
            "x": 560.0,
            "y": 310.0,
            "width": 160.0,
            "height": 70.0,
            "type": "Text Display",
            "properties": {
              "topic": "Robot/container/drive/frModule/turnPID/Accumulated error (units)",
              "period": 0.06,
              "data_type": "double",
              "show_submit_button": false
            }
          },
          {
            "title": "Setpoint position (units)",
            "x": 560.0,
            "y": 380.0,
            "width": 160.0,
            "height": 70.0,
            "type": "Text Display",
            "properties": {
              "topic": "Robot/container/drive/frModule/turnPID/Setpoint position (units)",
              "period": 0.06,
              "data_type": "double",
              "show_submit_button": false
            }
          },
          {
            "title": "Setpoint velocity (units per second)",
            "x": 560.0,
            "y": 450.0,
            "width": 150.0,
            "height": 70.0,
            "type": "Text Display",
            "properties": {
              "topic": "Robot/container/drive/frModule/turnPID/Setpoint velocity (units per second)",
              "period": 0.06,
              "data_type": "double",
              "show_submit_button": false
            }
          },
          {
            "title": "name",
            "x": 410.0,
            "y": 390.0,
            "width": 130.0,
            "height": 130.0,
            "type": "Text Display",
            "properties": {
              "topic": "Robot/container/drive/frModule/name",
              "period": 0.06,
              "data_type": "string",
              "show_submit_button": false
            }
          },
          {
            "title": "Position (units)",
            "x": 800.0,
            "y": 10.0,
            "width": 100.0,
            "height": 90.0,
            "type": "Text Display",
            "properties": {
              "topic": "Robot/container/drive/blModule/driveEncoder/Position (units)",
              "period": 0.06,
              "data_type": "double",
              "show_submit_button": false
            }
          },
          {
            "title": "Velocity (units per second)",
            "x": 800.0,
            "y": 100.0,
            "width": 100.0,
            "height": 70.0,
            "type": "Text Display",
            "properties": {
              "topic": "Robot/container/drive/blModule/driveEncoder/Velocity (units per second)",
              "period": 0.06,
              "data_type": "double",
              "show_submit_button": false
            }
          },
          {
            "title": "Error (units)",
            "x": 800.0,
            "y": 170.0,
            "width": 80.0,
            "height": 70.0,
            "type": "Text Display",
            "properties": {
              "topic": "Robot/container/drive/blModule/drivePID/Error (units)",
              "period": 0.06,
              "data_type": "double",
              "show_submit_button": false
            }
          },
          {
            "title": "Error over time (units per second)",
            "x": 800.0,
            "y": 240.0,
            "width": 140.0,
            "height": 70.0,
            "type": "Text Display",
            "properties": {
              "topic": "Robot/container/drive/blModule/drivePID/Error over time (units per second)",
              "period": 0.06,
              "data_type": "double",
              "show_submit_button": false
            }
          },
          {
            "title": "Accumulated error (units)",
            "x": 800.0,
            "y": 310.0,
            "width": 160.0,
            "height": 70.0,
            "type": "Text Display",
            "properties": {
              "topic": "Robot/container/drive/blModule/drivePID/Accumulated error (units)",
              "period": 0.06,
              "data_type": "double",
              "show_submit_button": false
            }
          },
          {
            "title": "Radians",
            "x": 1060.0,
            "y": 10.0,
            "width": 90.0,
            "height": 90.0,
            "type": "Text Display",
            "properties": {
              "topic": "Robot/container/drive/blModule/absoluteAngle/Radians",
              "period": 0.06,
              "data_type": "double",
              "show_submit_button": false
            }
          },
          {
            "title": "Position (units)",
            "x": 960.0,
            "y": 10.0,
            "width": 100.0,
            "height": 90.0,
            "type": "Text Display",
            "properties": {
              "topic": "Robot/container/drive/blModule/turnEncoder/Position (units)",
              "period": 0.06,
              "data_type": "double",
              "show_submit_button": false
            }
          },
          {
            "title": "Velocity (units per second)",
            "x": 960.0,
            "y": 100.0,
            "width": 90.0,
            "height": 70.0,
            "type": "Text Display",
            "properties": {
              "topic": "Robot/container/drive/blModule/turnEncoder/Velocity (units per second)",
              "period": 0.06,
              "data_type": "double",
              "show_submit_button": false
            }
          },
          {
            "title": "Error (units)",
            "x": 960.0,
            "y": 170.0,
            "width": 80.0,
            "height": 70.0,
            "type": "Text Display",
            "properties": {
              "topic": "Robot/container/drive/blModule/turnPID/Error (units)",
              "period": 0.06,
              "data_type": "double",
              "show_submit_button": false
            }
          },
          {
            "title": "Error over time (units per second)",
            "x": 960.0,
            "y": 240.0,
            "width": 140.0,
            "height": 70.0,
            "type": "Text Display",
            "properties": {
              "topic": "Robot/container/drive/blModule/turnPID/Error over time (units per second)",
              "period": 0.06,
              "data_type": "double",
              "show_submit_button": false
            }
          },
          {
            "title": "Accumulated error (units)",
            "x": 960.0,
            "y": 310.0,
            "width": 160.0,
            "height": 70.0,
            "type": "Text Display",
            "properties": {
              "topic": "Robot/container/drive/blModule/turnPID/Accumulated error (units)",
              "period": 0.06,
              "data_type": "double",
              "show_submit_button": false
            }
          },
          {
            "title": "Setpoint position (units)",
            "x": 960.0,
            "y": 380.0,
            "width": 160.0,
            "height": 70.0,
            "type": "Text Display",
            "properties": {
              "topic": "Robot/container/drive/blModule/turnPID/Setpoint position (units)",
              "period": 0.06,
              "data_type": "double",
              "show_submit_button": false
            }
          },
          {
            "title": "Setpoint velocity (units per second)",
            "x": 960.0,
            "y": 450.0,
            "width": 150.0,
            "height": 70.0,
            "type": "Text Display",
            "properties": {
              "topic": "Robot/container/drive/blModule/turnPID/Setpoint velocity (units per second)",
              "period": 0.06,
              "data_type": "double",
              "show_submit_button": false
            }
          },
          {
            "title": "name",
            "x": 870.0,
            "y": 390.0,
            "width": 80.0,
            "height": 90.0,
            "type": "Text Display",
            "properties": {
              "topic": "Robot/container/drive/blModule/name",
              "period": 0.06,
              "data_type": "string",
              "show_submit_button": false
            }
          },
          {
            "title": "Position (units)",
            "x": 1160.0,
            "y": 10.0,
            "width": 100.0,
            "height": 90.0,
            "type": "Text Display",
            "properties": {
              "topic": "Robot/container/drive/brModule/driveEncoder/Position (units)",
              "period": 0.06,
              "data_type": "double",
              "show_submit_button": false
            }
          },
          {
            "title": "Velocity (units per second)",
            "x": 1160.0,
            "y": 100.0,
            "width": 100.0,
            "height": 70.0,
            "type": "Text Display",
            "properties": {
              "topic": "Robot/container/drive/brModule/driveEncoder/Velocity (units per second)",
              "period": 0.06,
              "data_type": "double",
              "show_submit_button": false
            }
          },
          {
            "title": "Error (units)",
            "x": 1160.0,
            "y": 170.0,
            "width": 80.0,
            "height": 70.0,
            "type": "Text Display",
            "properties": {
              "topic": "Robot/container/drive/brModule/drivePID/Error (units)",
              "period": 0.06,
              "data_type": "double",
              "show_submit_button": false
            }
          },
          {
            "title": "Error over time (units per second)",
            "x": 1160.0,
            "y": 240.0,
            "width": 140.0,
            "height": 70.0,
            "type": "Text Display",
            "properties": {
              "topic": "Robot/container/drive/brModule/drivePID/Error over time (units per second)",
              "period": 0.06,
              "data_type": "double",
              "show_submit_button": false
            }
          },
          {
            "title": "Accumulated error (units)",
            "x": 1160.0,
            "y": 310.0,
            "width": 160.0,
            "height": 70.0,
            "type": "Text Display",
            "properties": {
              "topic": "Robot/container/drive/brModule/drivePID/Accumulated error (units)",
              "period": 0.06,
              "data_type": "double",
              "show_submit_button": false
            }
          },
          {
            "title": "Position (units)",
            "x": 1330.0,
            "y": 10.0,
            "width": 100.0,
            "height": 90.0,
            "type": "Text Display",
            "properties": {
              "topic": "Robot/container/drive/brModule/turnEncoder/Position (units)",
              "period": 0.06,
              "data_type": "double",
              "show_submit_button": false
            }
          },
          {
            "title": "Radians",
            "x": 1430.0,
            "y": 10.0,
            "width": 90.0,
            "height": 90.0,
            "type": "Text Display",
            "properties": {
              "topic": "Robot/container/drive/brModule/absoluteAngle/Radians",
              "period": 0.06,
              "data_type": "double",
              "show_submit_button": false
            }
          },
          {
            "title": "Velocity (units per second)",
            "x": 1330.0,
            "y": 100.0,
            "width": 100.0,
            "height": 70.0,
            "type": "Text Display",
            "properties": {
              "topic": "Robot/container/drive/brModule/turnEncoder/Velocity (units per second)",
              "period": 0.06,
              "data_type": "double",
              "show_submit_button": false
            }
          },
          {
            "title": "Error (units)",
            "x": 1330.0,
            "y": 170.0,
            "width": 80.0,
            "height": 70.0,
            "type": "Text Display",
            "properties": {
              "topic": "Robot/container/drive/brModule/turnPID/Error (units)",
              "period": 0.06,
              "data_type": "double",
              "show_submit_button": false
            }
          },
          {
            "title": "Error over time (units per second)",
            "x": 1330.0,
            "y": 240.0,
            "width": 140.0,
            "height": 70.0,
            "type": "Text Display",
            "properties": {
              "topic": "Robot/container/drive/brModule/turnPID/Error over time (units per second)",
              "period": 0.06,
              "data_type": "double",
              "show_submit_button": false
            }
          },
          {
            "title": "Accumulated error (units)",
            "x": 1330.0,
            "y": 310.0,
            "width": 160.0,
            "height": 70.0,
            "type": "Text Display",
            "properties": {
              "topic": "Robot/container/drive/brModule/turnPID/Accumulated error (units)",
              "period": 0.06,
              "data_type": "double",
              "show_submit_button": false
            }
          },
          {
            "title": "Setpoint position (units)",
            "x": 1330.0,
            "y": 380.0,
            "width": 160.0,
            "height": 70.0,
            "type": "Text Display",
            "properties": {
              "topic": "Robot/container/drive/brModule/turnPID/Setpoint position (units)",
              "period": 0.06,
              "data_type": "double",
              "show_submit_button": false
            }
          },
          {
            "title": "Setpoint velocity (units per second)",
            "x": 1330.0,
            "y": 450.0,
            "width": 150.0,
            "height": 70.0,
            "type": "Text Display",
            "properties": {
              "topic": "Robot/container/drive/brModule/turnPID/Setpoint velocity (units per second)",
              "period": 0.06,
              "data_type": "double",
              "show_submit_button": false
            }
          },
          {
            "title": "name",
            "x": 1180.0,
            "y": 390.0,
            "width": 130.0,
            "height": 130.0,
            "type": "Text Display",
            "properties": {
              "topic": "Robot/container/drive/brModule/name",
              "period": 0.06,
              "data_type": "string",
              "show_submit_button": false
            }
          }
        ]
      }
    },
    {
      "name": "Autonomous",
      "grid_layout": {
        "layouts": [],
        "containers": []
      }
    }
  ]
}